Workbook

Sheet How to Use
A1: Records Destruction & Close-Out Tracker
A3: Tabs
A4: Matter Tracker - one row per client/matter. Use it to get partner sign-off and track close-out letters and shredding.
A5: Box Register - one row per box. Assign each box to a matter and record the partner decision.
A6: Change Log - every cleanup change made to the original Master Record Sheet.
A7: Original - Matters / Original - Flagged - unchanged copies of the original tabs for reference.
A9: Yellow cells are for you to fill in. Everything else is either carried over from the original sheet or calculated.
A11: Workflow
A12: 1. Box Register: filter Box Type to "Needs ID", "Needs Matter Assignment" and "Mixed - Multiple Matters" and assign a Client and Matter to each box. "Names Mentioned" is a keyword hint only - confirm before relying on it.
A13: 2. Add any new client/matter to the Matter Tracker. The Box Register Matter must match the Matter Tracker Matter exactly for the box count to work.
A14: 3. Send each Responsible Partner their matters for approval. Before approving, confirm no protective order, litigation hold, or related active matter covers the files.
A15: 4. Once approved, send the client close-out letter and enter the date. The response deadline fills in automatically (days set below).
... A17: 6. Boxes flagged as possibly holding originals go back to the client, not to the shredder.
A19: Client response window (days) | B19: 30 | C19: Placeholder - set to the firm's retention-notice period.

Sheet Matter Tracker
A1: Client | B1: Matter | C1: Matter # | D1: # Boxes | E1: Responsible Partner | F1: Partner Approved | G1: Approval Date | H1: Close-Out Letter Sent | I1: Client Response Deadline | J1: Client Response | K1: Shred Date | L1: Destruction Certificate # | M1: Notes
A2: Optronic Technologies | B2: Optronic Technologies - Orion v Celestron Fraudulent Transfer Action - 11348 | C2: 11348 | D2: =COUNTIFS('Box Register'!$E:$E,$A2,'Box Register'!$F:$F,$B2) -> 54 | F2: Pending | I2: =IF(H2="","",H2+'How to Use'!$B$19) | J2: Pending
A3: Lyell Wealth | B3: Lyell Wealth - BNY/Atherton Litigation - 10416 | C3: 10416 | D3: =COUNTIFS('Box Register'!$E:$E,$A3,'Box Register'!$F:$F,$B3) -> 5 | F3: Pending | I3: =IF(H3="","",H3+'How to Use'!$B$19) | J3: Pending
A4: Once Upon a Farm | B4: Once Upon a Farm - Trademark - 15071 | C4: 15071 | D4: =COUNTIFS('Box Register'!$E:$E,$A4,'Box Register'!$F:$F,$B4) -> 3 | F4: Pending | I4: =IF(H4="","",H4+'How to Use'!$B$19) | J4: Pending
A5: Outdoorsy, Inc. | B5: Outdoorsy, Inc. - BFG Acquisition - 14862 | C5: 14862 | D5: =COUNTIFS('Box Register'!$E:$E,$A5,'Box Register'!$F:$F,$B5) -> 1 | F5: Pending | I5: =IF(H5="","",H5+'How to Use'!$B$19) | J5: Pending
A6: Pirate Brands | B6: Pirate Brands - Robert Ehrlich Dispute - 10173 | C6: 10173 | D6: =COUNTIFS('Box Register'!$E:$E,$A6,'Box Register'!$F:$F,$B6) -> 3 | F6: Pending | I6: =IF(H6="","",H6+'How to Use'!$B$19) | J6: Pending
A7: Polychain Capital LP | B7: Polychain Capital LP - General - 14573 | C7: 14573 | D7: =COUNTIFS('Box Register'!$E:$E,$A7,'Box Register'!$F:$F,$B7) -> 13 | F7: Pending | I7: =IF(H7="","",H7+'How to Use'!$B$19) | J7: Pending
A8: Carbon Investment Partners, LLC | B8: Carbon Investment Partners, LLC - Bressler Dispute - 10599 | C8: 10599 | D8: =COUNTIFS('Box Register'!$E:$E,$A8,'Box Register'!$F:$F,$B8) -> 7 | F8: Pending | I8: =IF(H8="","",H8+'How to Use'!$B$19) | J8: Pending
A9: B&G Foods | B9: B&G Foods - General - 10183 | C9: 10183 | D9: =COUNTIFS('Box Register'!$E:$E,$A9,'Box Register'!$F:$F,$B9) -> 2 | F9: Pending | I9: =IF(H9="","",H9+'How to Use'!$B$19) | J9: Pending
A10: Nature's Bakery | B10: Nature's Bakery | D10: =COUNTIFS('Box Register'!$E:$E,$A10,'Box Register'!$F:$F,$B10) -> 2 | F10: Pending | I10: =IF(H10="","",H10+'How to Use'!$B$19) | J10: Pending | M10: No matter # in original sheet
A11: Smashmallow, LLC | B11: Smashmallow, LLC - Wolfgang Confectioners Dispute - 11943 | C11: 11943 | D11: =COUNTIFS('Box Register'!$E:$E,$A11,'Box Register'!$F:$F,$B11) -> 3 | F11: Pending | I11: =IF(H11="","",H11+'How to Use'!$B$19) | J11: Pending
A12: Stephen Horn Insurance Services | B12: Stephen Horn Insurance Services - Employment - 12695 | C12: 12695 | D12: =COUNTIFS('Box Register'!$E:$E,$A12,'Box Register'!$F:$F,$B12) -> 1 | F12: Pending | I12: =IF(H12="","",H12+'How to Use'!$B$19) | J12: Pending
A13: Devoto-Wade LLC d/b/a Golden State Cider | B13: Devoto-Wade LLC d/b/a Golden State Cider - Fee Dispute - 14679 | C13: 14679 | D13: =COUNTIFS('Box Register'!$E:$E,$A13,'Box Register'!$F:$F,$B13) -> 6 | F13: Pending | I13: =IF(H13="","",H13+'How to Use'!$B$19) | J13: Pending
D14: =IF(B14="","",COUNTIFS('Box Register'!$E:$E,$A14,'Box Register'!$F:$F,$B14)) | I14: =IF(H14="","",H14+'How to Use'!$B$19)
D15: =IF(B15="","",COUNTIFS('Box Register'!$E:$E,$A15,'Box Register'!$F:$F,$B15)) | I15: =IF(H15="","",H15+'How to Use'!$B$19)
D16: =IF(B16="","",COUNTIFS('Box Register'!$E:$E,$A16,'Box Register'!$F:$F,$B16)) | I16: =IF(H16="","",H16+'How to Use'!$B$19)
D17: =IF(B17="","",COUNTIFS('Box Register'!$E:$E,$A17,'Box Register'!$F:$F,$B17)) | I17: =IF(H17="","",H17+'How to Use'!$B$19)
D18: =IF(B18="","",COUNTIFS('Box Register'!$E:$E,$A18,'Box Register'!$F:$F,$B18)) | I18: =IF(H18="","",H18+'How to Use'!$B$19)
D19: =IF(B19="","",COUNTIFS('Box Register'!$E:$E,$A19,'Box Register'!$F:$F,$B19)) | I19: =IF(H19="","",H19+'How to Use'!$B$19)
D20: =IF(B20="","",COUNTIFS('Box Register'!$E:$E,$A20,'Box Register'!$F:$F,$B20)) | I20: =IF(H20="","",H20+'How to Use'!$B$19)
D21: =IF(B21="","",COUNTIFS('Box Register'!$E:$E,$A21,'Box Register'!$F:$F,$B21)) | I21: =IF(H21="","",H21+'How to Use'!$B$19)
D22: =IF(B22="","",COUNTIFS('Box Register'!$E:$E,$A22,'Box Register'!$F:$F,$B22)) | I22: =IF(H22="","",H22+'How to Use'!$B$19)
D23: =IF(B23="","",COUNTIFS('Box Register'!$E:$E,$A23,'Box Register'!$F:$F,$B23)) | I23: =IF(H23="","",H23+'How to Use'!$B$19)
D24: =IF(B24="","",COUNTIFS('Box Register'!$E:$E,$A24,'Box Register'!$F:$F,$B24)) | I24: =IF(H24="","",H24+'How to Use'!$B$19)
D25: =IF(B25="","",COUNTIFS('Box Register'!$E:$E,$A25,'Box Register'!$F:$F,$B25)) | I25: =IF(H25="","",H25+'How to Use'!$B$19)
... D200: =IF(B200="","",COUNTIFS('Box Register'!$E:$E,$A200,'Box Register'!$F:$F,$B200)) | I200: =IF(H200="","",H200+'How to Use'!$B$19)

Sheet Box Register
A1: Box # | B1: Box Label | C1: Contents | D1: Names Mentioned (hint) | E1: Client | F1: Matter | G1: Box Type | H1: Responsible Partner | I1: Partner Decision | J1: Decision Date | K1: Issues to Resolve | L1: Notes | M1: Source in Original Sheet
A2: R101339072 | E2: Optronic Technologies | F2: Optronic Technologies - Orion v Celestron Fraudulent Transfer Action - 11348 | G2: Client File | I2: Pending | M2: Matters + Records row 2
A3: R101339073 | E3: Optronic Technologies | F3: Optronic Technologies - Orion v Celestron Fraudulent Transfer Action - 11348 | G3: Client File | I3: Pending | M3: Matters + Records row 3
A4: R101339074 | E4: Optronic Technologies | F4: Optronic Technologies - Orion v Celestron Fraudulent Transfer Action - 11348 | G4: Client File | I4: Pending | M4: Matters + Records row 4
A5: R101339075 | E5: Optronic Technologies | F5: Optronic Technologies - Orion v Celestron Fraudulent Transfer Action - 11348 | G5: Client File | I5: Pending | M5: Matters + Records row 5
A6: R101339076 | E6: Optronic Technologies | F6: Optronic Technologies - Orion v Celestron Fraudulent Transfer Action - 11348 | G6: Client File | I6: Pending | M6: Matters + Records row 6
A7: R101339077 | E7: Optronic Technologies | F7: Optronic Technologies - Orion v Celestron Fraudulent Transfer Action - 11348 | G7: Client File | I7: Pending | M7: Matters + Records row 7
A8: R101339078 | E8: Optronic Technologies | F8: Optronic Technologies - Orion v Celestron Fraudulent Transfer Action - 11348 | G8: Client File | I8: Pending | M8: Matters + Records row 8
A9: R101339079 | E9: Optronic Technologies | F9: Optronic Technologies - Orion v Celestron Fraudulent Transfer Action - 11348 | G9: Client File | I9: Pending | M9: Matters + Records row 9
A10: R101339080 | E10: Optronic Technologies | F10: Optronic Technologies - Orion v Celestron Fraudulent Transfer Action - 11348 | G10: Client File | I10: Pending | M10: Matters + Records row 10
A11: R101339081 | E11: Optronic Technologies | F11: Optronic Technologies - Orion v Celestron Fraudulent Transfer Action - 11348 | G11: Client File | I11: Pending | M11: Matters + Records row 11
A12: R101339082 | E12: Optronic Technologies | F12: Optronic Technologies - Orion v Celestron Fraudulent Transfer Action - 11348 | G12: Client File | I12: Pending | M12: Matters + Records row 12
A13: R101339083 | E13: Optronic Technologies | F13: Optronic Technologies - Orion v Celestron Fraudulent Transfer Action - 11348 | G13: Client File | I13: Pending | M13: Matters + Records row 13
... A40: R102648132 | E40: Optronic Technologies | F40: Optronic Technologies - Orion v Celestron Fraudulent Transfer Action - 11348 | G40: Client File | I40: Pending | M40: Matters + Records row 40
A41: R102354511 | E41: Optronic Technologies | F41: Optronic Technologies - Orion v Celestron Fraudulent Transfer Action - 11348 | G41: Client File | I41: Pending | K41: Box # also listed at Matters + Records row 56 | M41: Matters + Records row 41
A42: R102648295 | E42: Optronic Technologies | F42: Optronic Technologies - Orion v Celestron Fraudulent Transfer Action - 11348 | G42: Client File | I42: Pending | K42: Box # also listed at Matters + Records row 97, Flagged Issues row 175 | M42: Matters + Records row 42
A43: R102648156 | E43: Optronic Technologies | F43: Optronic Technologies - Orion v Celestron Fraudulent Transfer Action - 11348 | G43: Client File | I43: Pending | K43: Box # also listed at Flagged Issues row 154 | M43: Matters + Records row 43
A44: R101399104 | E44: Optronic Technologies | F44: Optronic Technologies - Orion v Celestron Fraudulent Transfer Action - 11348 | G44: Client File | I44: Pending | M44: Matters + Records row 44
A45: R101399103 | E45: Optronic Technologies | F45: Optronic Technologies - Orion v Celestron Fraudulent Transfer Action - 11348 | G45: Client File | I45: Pending | M45: Matters + Records row 45
A46: R101399105 | E46: Optronic Technologies | F46: Optronic Technologies - Orion v Celestron Fraudulent Transfer Action - 11348 | G46: Client File | I46: Pending | M46: Matters + Records row 46
A47: R102648138 | E47: Optronic Technologies | F47: Optronic Technologies - Orion v Celestron Fraudulent Transfer Action - 11348 | G47: Client File | I47: Pending | M47: Matters + Records row 47
A48: R102648139 | E48: Optronic Technologies | F48: Optronic Technologies - Orion v Celestron Fraudulent Transfer Action - 11348 | G48: Client File | I48: Pending | M48: Matters + Records row 48
A49: R101339111 | E49: Optronic Technologies | F49: Optronic Technologies - Orion v Celestron Fraudulent Transfer Action - 11348 | G49: Client File | I49: Pending | M49: Matters + Records row 49
A50: R102648136 | E50: Optronic Technologies | F50: Optronic Technologies - Orion v Celestron Fraudulent Transfer Action - 11348 | G50: Client File | I50: Pending | M50: Matters + Records row 50
A51: R102648141 | E51: Optronic Technologies | F51: Optronic Technologies - Orion v Celestron Fraudulent Transfer Action - 11348 | G51: Client File | I51: Pending | M51: Matters + Records row 51
A52: R102648135 | E52: Optronic Technologies | F52: Optronic Technologies - Orion v Celestron Fraudulent Transfer Action - 11348 | G52: Client File | I52: Pending | M52: Matters + Records row 52
A53: R102648140 | E53: Optronic Technologies | F53: Optronic Technologies - Orion v Celestron Fraudulent Transfer Action - 11348 | G53: Client File | I53: Pending | M53: Matters + Records row 53
A54: R102648289 | E54: Optronic Technologies | F54: Optronic Technologies - Orion v Celestron Fraudulent Transfer Action - 11348 | G54: Client File | I54: Pending | M54: Matters + Records row 54
A55: R102648290 | E55: Optronic Technologies | F55: Optronic Technologies - Orion v Celestron Fraudulent Transfer Action - 11348 | G55: Client File | I55: Pending | M55: Matters + Records row 55
A56: R102354511 | E56: Lyell Wealth | F56: Lyell Wealth - BNY/Atherton Litigation - 10416 | G56: Client File | I56: Pending | K56: Box # also listed at Matters + Records row 41 | M56: Matters + Records row 56
A57: R102354498 | E57: Lyell Wealth | F57: Lyell Wealth - BNY/Atherton Litigation - 10416 | G57: Client File | I57: Pending | M57: Matters + Records row 57
A58: R102354582 | E58: Lyell Wealth | F58: Lyell Wealth - BNY/Atherton Litigation - 10416 | G58: Client File | I58: Pending | M58: Matters + Records row 58
A59: R102648294 | E59: Lyell Wealth | F59: Lyell Wealth - BNY/Atherton Litigation - 10416 | G59: Client File | I59: Pending | K59: Box # also listed at Flagged Issues row 178 | M59: Matters + Records row 59
A60: R102354530 | E60: Lyell Wealth | F60: Lyell Wealth - BNY/Atherton Litigation - 10416 | G60: Client File | I60: Pending | L60: Was spelled "cyell" | M60: Matters + Records row 60
A61: R102354512 | E61: Once Upon a Farm | F61: Once Upon a Farm - Trademark - 15071 | G61: Client File | I61: Pending | M61: Matters + Records row 64
A62: R102354513 | E62: Once Upon a Farm | F62: Once Upon a Farm - Trademark - 15071 | G62: Client File | I62: Pending | M62: Matters + Records row 65
A63: R102354515 | E63: Once Upon a Farm | F63: Once Upon a Farm - Trademark - 15071 | G63: Client File | I63: Pending | M63: Matters + Records row 66
A64: R102354499 | E64: Outdoorsy, Inc. | F64: Outdoorsy, Inc. - BFG Acquisition - 14862 | G64: Client File | I64: Pending | K64: Box # also listed at Flagged Issues row 145 | M64: Matters + Records row 67
A65: R102354500 | E65: Pirate Brands | F65: Pirate Brands - Robert Ehrlich Dispute - 10173 | G65: Client File | I65: Pending | M65: Matters + Records row 68
A66: R102282381 | E66: Pirate Brands | F66: Pirate Brands - Robert Ehrlich Dispute - 10173 | G66: Client File | I66: Pending | K66: Box # also listed at Flagged Issues row 288 | M66: Matters + Records row 69
A67: R102354502 | E67: Pirate Brands | F67: Pirate Brands - Robert Ehrlich Dispute - 10173 | G67: Client File | I67: Pending | L67: Contains files for other matters as well | M67: Matters + Records row 70
A68: R102648133 | E68: Polychain Capital LP | F68: Polychain Capital LP - General - 14573 | G68: Client File | I68: Pending | M68: Matters + Records row 71
A69: R101339109 | E69: Polychain Capital LP | F69: Polychain Capital LP - General - 14573 | G69: Client File | I69: Pending | M69: Matters + Records row 72
A70: R102648114 | E70: Polychain Capital LP | F70: Polychain Capital LP - General - 14573 | G70: Client File | I70: Pending | M70: Matters + Records row 73
A71: R102648115 | E71: Polychain Capital LP | F71: Polychain Capital LP - General - 14573 | G71: Client File | I71: Pending | M71: Matters + Records row 74
A72: R102648116 | E72: Polychain Capital LP | F72: Polychain Capital LP - General - 14573 | G72: Client File | I72: Pending | M72: Matters + Records row 75
A73: R102648117 | E73: Polychain Capital LP | F73: Polychain Capital LP - General - 14573 | G73: Client File | I73: Pending | M73: Matters + Records row 76
A74: R102648118 | E74: Polychain Capital LP | F74: Polychain Capital LP - General - 14573 | G74: Client File | I74: Pending | M74: Matters + Records row 77
A75: R102648119 | E75: Polychain Capital LP | F75: Polychain Capital LP - General - 14573 | G75: Client File | I75: Pending | M75: Matters + Records row 78
A76: R102648120 | E76: Polychain Capital LP | F76: Polychain Capital LP - General - 14573 | G76: Client File | I76: Pending | M76: Matters + Records row 79
A77: R102648121 | E77: Polychain Capital LP | F77: Polychain Capital LP - General - 14573 | G77: Client File | I77: Pending | M77: Matters + Records row 80
A78: R102648122 | E78: Polychain Capital LP | F78: Polychain Capital LP - General - 14573 | G78: Client File | I78: Pending | M78: Matters + Records row 81
A79: R102648123 | E79: Polychain Capital LP | F79: Polychain Capital LP - General - 14573 | G79: Client File | I79: Pending | M79: Matters + Records row 82
... A83: R102354514 | E83: Carbon Investment Partners, LLC | F83: Carbon Investment Partners, LLC - Bressler Dispute - 10599 | G83: Client File | I83: Pending | M83: Matters + Records row 86
A84: R102648299 | E84: Carbon Investment Partners, LLC | F84: Carbon Investment Partners, LLC - Bressler Dispute - 10599 | G84: Client File | I84: Pending | K84: Box # also listed at Flagged Issues row 172 | M84: Matters + Records row 87
A85: R101399106 | E85: Carbon Investment Partners, LLC | F85: Carbon Investment Partners, LLC - Bressler Dispute - 10599 | G85: Client File | I85: Pending | M85: Matters + Records row 88
A86: R102648144 | E86: Carbon Investment Partners, LLC | F86: Carbon Investment Partners, LLC - Bressler Dispute - 10599 | G86: Client File | I86: Pending | M86: Matters + Records row 89
A87: R102648143 | E87: Carbon Investment Partners, LLC | F87: Carbon Investment Partners, LLC - Bressler Dispute - 10599 | G87: Client File | I87: Pending | M87: Matters + Records row 90
A88: R102648306 | E88: B&G Foods | F88: B&G Foods - General - 10183 | G88: Client File | I88: Pending | K88: Box # also listed at Flagged Issues row 160 | M88: Matters + Records row 91
A89: R102648305 | E89: B&G Foods | F89: B&G Foods - General - 10183 | G89: Client File | I89: Pending | K89: Box # also listed at Flagged Issues row 162 | M89: Matters + Records row 92
A90: R102648303 | E90: Nature's Bakery | F90: Nature's Bakery | G90: Client File | I90: Pending | K90: Box # also listed at Flagged Issues row 168 | M90: Matters + Records row 93
A91: R102648157 | E91: Nature's Bakery | F91: Nature's Bakery | G91: Client File | I91: Pending | K91: Box # also listed at Flagged Issues row 165 | M91: Matters + Records row 94
A92: R102648311 | E92: Smashmallow, LLC | F92: Smashmallow, LLC - Wolfgang Confectioners Dispute - 11943 | G92: Client File | I92: Pending | K92: Box # also listed at Flagged Issues row 172 | M92: Matters + Records row 95
A93: R102648310 | E93: Smashmallow, LLC | F93: Smashmallow, LLC - Wolfgang Confectioners Dispute - 11943 | G93: Client File | I93: Pending | K93: Box # also listed at Flagged Issues row 172 | M93: Matters + Records row 96
A94: R102648295 | E94: Smashmallow, LLC | F94: Smashmallow, LLC - Wolfgang Confectioners Dispute - 11943 | G94: Client File | I94: Pending | K94: Box # also listed at Matters + Records row 42, Flagged Issues row 175 | M94: Matters + Records row 97
A95: R102354578 | E95: Stephen Horn Insurance Services | F95: Stephen Horn Insurance Services - Employment - 12695 | G95: Client File | I95: Pending | M95: Matters + Records row 98
A96: R102648292 | E96: Devoto-Wade LLC d/b/a Golden State Cider | F96: Devoto-Wade LLC d/b/a Golden State Cider - Fee Dispute - 14679 | G96: Client File | I96: Pending | M96: Matters + Records row 99
A97: R102648288 | E97: Devoto-Wade LLC d/b/a Golden State Cider | F97: Devoto-Wade LLC d/b/a Golden State Cider - Fee Dispute - 14679 | G97: Client File | I97: Pending | M97: Matters + Records row 100
A98: R102648287 | E98: Devoto-Wade LLC d/b/a Golden State Cider | F98: Devoto-Wade LLC d/b/a Golden State Cider - Fee Dispute - 14679 | G98: Client File | I98: Pending | M98: Matters + Records row 101
A99: R102648286 | E99: Devoto-Wade LLC d/b/a Golden State Cider | F99: Devoto-Wade LLC d/b/a Golden State Cider - Fee Dispute - 14679 | G99: Client File | I99: Pending | M99: Matters + Records row 102
A100: R102648285 | E100: Devoto-Wade LLC d/b/a Golden State Cider | F100: Devoto-Wade LLC d/b/a Golden State Cider - Fee Dispute - 14679 | G100: Client File | I100: Pending | M100: Matters + Records row 103
A101: R102648284 | E101: Devoto-Wade LLC d/b/a Golden State Cider | F101: Devoto-Wade LLC d/b/a Golden State Cider - Fee Dispute - 14679 | G101: Client File | I101: Pending | M101: Matters + Records row 104
A102: R102354638 | B102: Marsha Davis v. AG Seal Beach | C102: Binders case | D102: Marsha, Davis | G102: Needs Matter Assignment | I102: Pending | M102: Flagged Issues row 2
A103: R102354637 | B103: No Label | C103: Misc binders, Redwells | G103: Needs ID | I103: Pending | M103: Flagged Issues row 3
A104: R102354636 | B104: No Label | C104: Misc binders, Redwells | G104: Needs ID | I104: Pending | M104: Flagged Issues row 4
A105: R102354635 | B105: Arctic/Garrett Blood tossed Goblenberg | C105: transcripts | D105: Arctic, Goblenb | G105: Needs Matter Assignment | I105: Pending | M105: Flagged Issues row 5
A106: R102354634 | B106: Marsha Davis v. AG Seal Beach | C106: Exhibit Binders | D106: Marsha, Davis | G106: Needs Matter Assignment | I106: Pending | M106: Flagged Issues row 6
A107: R102354633 | B107: Exhibits | C107: Exhibit Binders | G107: Needs ID | I107: Pending | M107: Flagged Issues row 7
A108: R102354632 | B108: Exhibits | C108: Exhibit Binders | G108: Needs ID | I108: Pending | M108: Flagged Issues row 8
A109: R102354631 | B109: Exhibits | C109: Exhibit Binders | G109: Needs ID | I109: Pending | M109: Flagged Issues row 9
A110: R102354630 | B110: Exhibits | C110: Exhibit Binders | G110: Needs ID | I110: Pending | M110: Flagged Issues row 10
A111: R102354629 | B111: Exhibits | C111: Exhibit Binders | G111: Needs ID | I111: Pending | M111: Flagged Issues row 11
A112: R102354628 | B112: Exhibits | C112: Exhibit Binders | G112: Needs ID | I112: Pending | M112: Flagged Issues row 12
A113: R102354627 | B113: Exhibits | C113: Exhibit Binders | G113: Needs ID | I113: Pending | M113: Flagged Issues row 13
A114: R102354626 | B114: delman box #2 | C114: Redwells w/ Docs. | D114: Delman | G114: Needs Matter Assignment | I114: Pending | M114: Flagged Issues row 14
A115: R102354625 | B115: Post it "Davis" | C115: Misc Docs. | D115: Davis | G115: Needs Matter Assignment | I115: Pending | M115: Flagged Issues row 15
A116: R102354624 | B116: No Label | C116: Misc Docs. | G116: Needs ID | I116: Pending | M116: Flagged Issues row 16
A117: R102354623 | B117: Aleah Box # 11 | C117: Depo Transcripts | D117: Aleah | G117: Needs Matter Assignment | I117: Pending | M117: Flagged Issues row 17
A118: R102354622 | B118: Job # SFB-100105 | C118: Misc Arctic o Docs | D118: Arctic | G118: Needs Matter Assignment | I118: Pending | M118: Flagged Issues row 18
A119: R102354621 | B119: Aleah Box # 5 | C119: Misc Docs. | D119: Aleah | G119: Needs Matter Assignment | I119: Pending | M119: Flagged Issues row 19
A120: R102354620 | B120: Aleah Box # 3 | C120: Exhibits | D120: Aleah | G120: Needs Matter Assignment | I120: Pending | M120: Flagged Issues row 20
A121: R102354619 | B121: No Label | C121: CD's | G121: Needs ID | I121: Pending | M121: Flagged Issues row 21
A122: R102354618 | B122: No Label | C122: CD's | G122: Needs ID | I122: Pending | M122: Flagged Issues row 22
A123: R102354617 | B123: JWH files #2 | C123: Misc | G123: Needs ID | I123: Pending | M123: Flagged Issues row 23
A124: R102354616 | B124: JWH files #4 | C124: Misc | G124: Needs ID | I124: Pending | M124: Flagged Issues row 24
A125: R102354615 | B125: JWH files #1 | C125: Misc | G125: Needs ID | I125: Pending | M125: Flagged Issues row 25
A126: R102354614 | B126: JWH files #6 | C126: Misc | G126: Needs ID | I126: Pending | M126: Flagged Issues row 26
A127: R10131528 | B127: clinted ID: #4 Roberts American Gourmet food box #2 | C127: Misc | D127: Roberts American | G127: Needs Matter Assignment | I127: Pending | K127: Box # has wrong number of digits | M127: Flagged Issues row 27
A128: R101331530 | B128: clinted ID: #4 Roberts American Gourmet food box #4 | C128: Misc | D128: Roberts American | G128: Needs Matter Assignment | I128: Pending | M128: Flagged Issues row 28
A129: R102354613 | B129: No Label | C129: Misc | G129: Needs ID | I129: Pending | M129: Flagged Issues row 29
...

Sheet Change Log
A1: Change
A2: Client and matter names filled down to every box on the Matters + Records tab (previously only on the first row of each matter).
A3: Both original tabs combined into one Box Register, one row per box.
A4: Rows with no box # that only continued the previous box (blank or "Previous entry continued") merged into that box's Contents.
A5: Cells listing several box numbers split into one row per box.
A6: Box numbers kept as written otherwise; any box # with the wrong number of digits or listed more than once is flagged in Issues to Resolve, not changed.
A7: Flagged Issues row 6: removed sequence prefix from '1-R102354634'
A8: Flagged Issues row 7: removed sequence prefix from '2-R102354633'
A9: Flagged Issues row 8: removed sequence prefix from '3-R102354632'
A10: Flagged Issues row 9: removed sequence prefix from '4-R102354631'
A11: Flagged Issues row 10: removed sequence prefix from '5-R102354630'
A12: Flagged Issues row 11: removed sequence prefix from '6-R102354629'
... A36: Flagged Issues row 135: removed exact duplicate of box R102354518

Sheet Original - Matters
A1: Client Name | B1: Matter Name | C1: Closed Date | D1: Matter Status | E1: Offsite Storage (Y/N) | F1: Box Skewer # | G1: Notes
A2: Optronic Technologies | B2: Optronic Technologies - Orion v Celestron Fraudulent Transfer Action - 11348 | C2: N/a | D2: N/a | E2: Yes | F2: R101339072
F3: R101339073
F4: R101339074
F5: R101339075
F6: R101339076
F7: R101339077
F8: R101339078
F9: R101339079
F10: R101339080
F11: R101339081
F12: R101339082
F13: R101339083
F14: R101339084
... F55: R102648290
A56: Lyell Wealth | B56: Lyell Wealth - BNY/Atherton Litigation - 10416 | C56: N/a | D56: N/a | E56: Yes | F56: R102354511
F57: R102354498
F58: R102354582
F59: R102648294
F60: R102354530 | G60: Was spelled "cyell"
A64: Once Upon a Farm | B64: Once Upon a Farm - Trademark - 15071 | C64: N/a | D64: N/a | E64: Yes | F64: R102354512
F65: R102354513
F66: R102354515
A67: Outdoorsy, Inc. | B67: Outdoorsy, Inc. - BFG Acquisition - 14862 | C67: N/a | D67: N/a | E67: Yes | F67: R102354499
A68: Pirate Brands | B68: Pirate Brands - Robert Ehrlich Dispute - 10173 | F68: R102354500
F69: R102282381
F70: R102354502 | G70: Contains files for other matters as well
A71: Polychain Capital LP | B71: Polychain Capital LP - General - 14573 | C71: N/a | D71: N/a | E71: Yes | F71: R102648133
F72: R101339109
F73: R102648114
F74: R102648115
F75: R102648116
F76: R102648117
F77: R102648118
F78: R102648119
F79: R102648120
F80: R102648121
F81: R102648122
F82: R102648123
F83: R102648124
A84: Carbon Investment Partners, LLC | B84: Carbon Investment Partners, LLC - Bressler Dispute - 10599 | C84: N/a | D84: N/a | E84: Yes | F84: R102354516
F85: R102354510
F86: R102354514
F87: R102648299
F88: R101399106
F89: R102648144
F90: R102648143
A91: B&G Foods | B91: B&G Foods - General - 10183 | C91: N/a | D91: N/a | E91: Yes | F91: R102648306
F92: R102648305
A93: Nature's Bakery | B93: Nature's Bakery | C93: N/a | D93: N/a | E93: Yes | F93: R102648303
F94: R102648157
A95: Smashmallow, LLC | B95: Smashmallow, LLC - Wolfgang Confectioners Dispute - 11943 | C95: N/a | D95: N/a | E95: Yes | F95: R102648311
F96: R102648310
F97: R102648295
A98: Stephen Horn Insurance Services | B98: Stephen Horn Insurance Services - Employment - 12695 | C98: N/a | D98: N/a | E98: Yes | F98: R102354578
A99: Devoto-Wade LLC d/b/a Golden State Cider | B99: Devoto-Wade LLC d/b/a Golden State Cider - Fee Dispute - 14679 | C99: N/a | D99: N/a | E99: Yes | F99: R102648292
F100: R102648288
F101: R102648287
F102: R102648286
F103: R102648285
F104: R102648284

Sheet Original - Flagged
A1: Box Label | B1: Skew Number | C1: Box Contents
A2: Marsha Davis v. AG Seal Beach | B2: R102354638 | C2: Binders case
A3: No Label | B3: R102354637 | C3: Misc binders, Redwells
A4: No Label | B4: R102354636 | C4: Misc binders, Redwells
A5: Arctic/Garrett Blood tossed Goblenberg | B5: R102354635 | C5: transcripts
A6: Marsha Davis v. AG Seal Beach | B6: 1-R102354634 | C6: Exhibit Binders
A7: Exhibits | B7: 2-R102354633 | C7: Exhibit Binders
A8: Exhibits | B8: 3-R102354632 | C8: Exhibit Binders
A9: Exhibits | B9: 4-R102354631 | C9: Exhibit Binders
A10: Exhibits | B10: 5-R102354630 | C10: Exhibit Binders
A11: Exhibits | B11: 6-R102354629 | C11: Exhibit Binders
A12: Exhibits | B12: 7-R102354628 | C12: Exhibit Binders
... A154: Misc Client Docs From Front Desk | B154: R102648156 | C154: Front Desk files- Stone Social Media - Stone
C155: Front Desk Files- Orion Exhibits - Orion
C156: Front Desk Files- Stone Ex. Depo - Stone
C157: Returned to shipper on via Fedex International
C158: Returned to shipper on via Fedex International
C159: Returned to shipper on via Fedex International
A160: JNH 4/26/2019 - Misc. Documents: Dravis, SkinnyPop, B&G Foods | B160: R102648306 | C160: 1 Box: - Dravis Telling Points - Horton/B&G/Cream of Wheat - SkinnyPop Trademark Services
A161: "Corporate Files" - Krisha's Desk Files | B161: R102648307 | C161: 1 Box: - Misc docs from Steeped/Special Tea, M& C Organics, and Homerun Inc.
A162: Toby's Files - DGL, B&G, Daily Harvest | B162: R102648305 | C162: 1 Box: - B&G Redwell - Daily Harvest Spiral Book - DGL Settlement Agreement & Several Transcripts
A163: Admin Mail | B163: R102648312 | C163: 1 Box: - Admin Mail 12/13/2018 - 12/23/2019
A164: Elliot Mail 2019 | B164: R102648158 | C164: Energy Future Holding Mail from 2018-2019
A165: AH - Client Docs Box #1 | B165: R102648157 | C165: 1 Box Research Reports: -Revive, Natures Bakery, Oat Mega, Skinny: Pt 1 & 2 Redwells: -New Nutrition Facts Panels -Humane Corp Docs -Pofential Clients
A166: AH - Client Docs Box #2 | B166: R102648159 | C166: 1 Box Folders: -JGF Conversation -JGF Employment Argument -BAV Renewal Milk Doc -Fresh from Farm to Family OUAF -DDG: Morning greens Misc. Client Redwells Pea Protein Binder (Amplify) Nurtur Me Corp. Redwell
A167: Legal Mail - 2018/2019 | B167: R102648154 | C167: 9/28/2018 - 12/3/2018
A168: Noah's Files - Elliot (1 box), Small, Nulo, Nature's Bakery (1 box) | B168: Elliot Box (1) - R102648309 Box (3) - R102648303 | C168: Box #1: ELLIOT - Redwelds -- Disclosure Statement, Law 360 Articles re. Proceedings, Other Dispute Cases, Elliot Misc: Cases, Motion to Reconsider: Order Approving Next Era Termination Fee - Manila Folders -- Professional Fees, Deadlines & Hearings Fee Committee re. Final Fee Applications, Misc. Notebook, Godfrey & Kahn Memo re. Fee Committee Process, Conflict Research, Fee Committee Plan, Certification of Counsel re. Motion to Appoint, Elliot Motion, Final T-Side Fees Awards, Busy Beaver, Carroll, Kravitz: Cross Exam, Legal Pad: Floor, FV-VCC Selection, Research: re. Conflicts (x2), Transcripts Box #3: NULO / NATURE'S BAKERY / SMALL V. KELLET Small v. Kellet - Misc. Loose Docs, Legal Pad Notes, Estate Dispute - Misc. Copies/Case Folders, Overview, KCM Legal NULO - ABC7, Backup, Misc. Manila Folders (x3) NATURE'S BAKERY - NB Dispute Folders (x2) - NB Misc.
A169: Dan Harris Client Files | B169: R102648308 | C169: Corodata Box - Dan Harris Client Docs - Tahi Tech - General Corporate Materials (redwell & binder)
A170: Correspondence Binders for Bicent | B170: R102648301 | C170: Correspondence Binders for Bicent (x3)
A171: Grenade, Rosenbood, Humane, Bibeault Stanley | B171: R102648300 | C171: Grenade Envelope : ERC v. Grenade Phyllis Dunwoody 8/10/2017 TSG Video Transcript Christian Heptinstall 8/11/2017 TSG Video Transcript Deposition of Greg Madsen 8/9/2017 TSG Video Transcript Rosenblood: Misc. Gerard Fox Law v. Rosenblood documents Bibeauth: Moloc v. Bobeault Moloco's RFPD #1 Docs Produced in Reponse to White RFPD CD. Amie Stanley Binder: transcript of Stanley v. Jacqueline Burks 2/16/18
... A176: Admin Mail 2018 | B176: R102648298 | C176: (1/23/2017 - 2/13/2019)
A177: Legal Mail 2018 | B177: R102648297
A178: Box 1 of 3 - Lyell & eCurrency | B178: R102648294 | C178: BNY Mellon v. Lyell Wealth Wealth Management Jury Instruction Binder Eat Real Food LLC (DBA Culina) - Series Seed Financing - May 10 2018 Fed Project/Other Redwell Commuications, Cross Compliant, CA Statues, Irish Law, Demurr, Derivative Redwell M&C emails - lyell; lyell/Chron, Lyell-KS, Lyell - M/C + work Product Redwell
A179: Artic Zero v. Aspen Hills Transcript - 12/4/2018 | B179: R102648293 | C179: Videotaped Depo of Nancy Jo Lundeen - 12/4/2018 (and CD) Videotaped Depo of Thomas Lundeen Volume 2 - 12/4/2018 (and CD) Videotaped Depo of Thomas Lundeen - 12/3/2018
A180: AH- Docs Box # 1 | B180: R102354494
A181: AH- Docs Box # 2 | B181: R102354493
A182: AH- Docs Box # 3 | B182: R102354492
A183: AH- Docs Box # 4 | B183: R102354491
A184: BraunHagey & B fye 12/31/17 | B184: R102354490 | C184: ficis account stain, misc invoices, experise R.
A185: AL- Client Binders Box # 1 | B185: R102354489 | C185: Empower v. Solarblue, judgement enforcement, visually - working border, Garrison - litigation, autodidactio + slands, cypress v. red oak, Daily Harvest - work binder
A186: AL- Client Binders Box # 2 | B186: R102354488 | C186: Hency v. sopko, elliott, corres. (x2), Elliott, plan and DSCI, Blocktowers, cyustavo dis, Garrison work binder
A187: AL- Client Binders Box # 3 | B187: R102354487 | C187: Ecurrency v. Ford, wano wk.B., empower v. solarblue wrk., eccurency stim appry
A188: AL- Client Redwells Box # 1 | B188: R102354486 | C188: Empower energy solarblue lit., empower enforcement of judge, Nature's Battery, Ecurrency, Autodidative, Dilley v. Gorlien, garrison client docs, DH v. Imperial, 7/27/18 PI Breifing, Mike Press, Baker Ave, JS
A189: AL- Client Redwells Box # 2 | B189: R102354475, sup- Neo Merilian | C189: Ghali Res + Policies, Ghali potential EXS, Efit, Elliott Res, Elliott
A190: AL- client Redwells + Spiral Binded Docs box # 3 | B190: R102354484 | C190: Redwells: Ghali- Client Docs, Tiarht, Lawrance warbot- Passport capit (x3), HRT Petroleum, cutpick energy
A191: RH- Client Docs. + Bin | B191: R102354483 | C191: Genband v. Impac. Hot Docs Bird, Genband- depo transcripts, Outdoorsy Redwell- CA case law, Tesselated
A192: SC Office Box 1 | B192: R102354482 | C192: Redwell: UMG- Hwan, Renee 2016-11-8 San Mateo Court lyell, Carlos Ortega Docs (orig), Garrison Investment
A193: EC- Legal Mail 6/20-9/24 | B193: R102354481
A194: EC- Misc Mail 6/18, 9/18, Single, Elliott, Greg, Onion | B194: R102354480
A195: Priest/Picchi- SF welding | B195: R102354479
A196: Preist/Picchi- DLA Piper. SF welding files | B196: R102354478
A197: Priest/Picchi client files | B197: R102354495
A198: WFC client files 10 of 17 | B198: R102354497
A199: Rosenblood Redwells & Binders (AL) | B199: R102354442 | C199: Rosenblood MSJ materials Redwells "claimants MSJ", Rosenblood Disco Motion/cases -> redwell, Gerard Fox v. Rosenblood Telephonic hearing Binder
A200: Rosenblood Binders (AL) | B200: R102354441 | C200: Rosenblood Expert Report Binder, Rosenblood AL Exhibit Binder
A201: Misc. Binders (AL & JNH) | B201: R102354440 | C201: Bold v. Goldman Sachs (ramsey dispute) working binder, DGL Binder, Smashmallow Hot Docs Binders #1 & #2
A202: Allison Hagey Boxes Corodata #1 | B202: R102354494 | C202: crowdfunding file, bluesky file, del llc code file, CA llc code file, series A financing for corp. financing ref, black acorn venture-client docs Redwell, OUAF corporate doc Redwell
A203: Previous entry continued | C203: Native cos Corporate dox Redwell, NB corporate doc Redwell, Folder "ever after" TM "Nulo" TM, "Green Joy", urban remedy notes, Gottfried recall notes, Folders: Lord Nut; Peanuts
A204: Previous entry continued | C204: Dave Peters: eat fried veggiesm emmer & co - Jesse Solomon, Ladera Foods - Brian Tetrud, Misc Notes Folder, Tam Tam Bora
A205: Allison Hagey Boxes Corodata #2 | B205: R102354493 | C205: B&G: Cream of Wheat Redwell, Rustic Bakery Redwell bylaws TM AA, Redwell for "search results for skinny", amplify Redwell (includes paqui, skinnycakes, tyrrells)
A206: Previous entry continued | C206: amplify corporate redwell, OUAF corp. Redwell, OUAF sereies A 3rd close Redwell
A207: Allison Hagey Boxes Corodata #3 | B207: R102354492 | C207: OUAF/Bright Bar & other Misc. Docs Redwell, research reports: storybrook smoothie, Native, be well x2, sonoma brands, Natures Bakery, uust carrots, chameleon cold brew, design of a chameleon, sust beets
A208: Allison Hagey Boxes Corodata #4 | B208: R102354491 | C208: Chameleon Corp Redwell, Be Well Corp Redwell, crowdfunding final rule, organic farming manual, taste what youre missing book one entrepreneur's take on leadership,
A209: Previous entry continued | C209: social media & self awareness book, thwarting consumer choice, cooking up a buisness, nine principles of litigation & life, black's law dictionary
A210: RF - Offsite - Box 5 of 5 | B210: R101399107 | C210: Beanitos Chronology Binder; Misc. Arbitrator List Binder
A211: MBB Office | B211: R102648134 | C211: Peter Ni Cross-Examination Binder; Cross Examination of Peter Ni; Misc. Loose Docs; Jury Instructions Binder; RJN Manila Folders
A212: JNH Desk | B212: R102648137 | C212: Admitted Trial Exhibits Binder Days 1-6; MSJ Declarations and Exhibits (Vol.1)
A213: JNH Office | B213: R102648142 | C213: DGDG/Ahmed Fattouh JNH Desk Binder; Ahmed Redwell; Ahmed Marriage of Del Grande Folder; Kent Lake Capital Chronology Documents Binder + Notes
A214: Taylor's Office | C214: Box 1: Humm Kombucha Distribution Agreement Binder; MISC Nulo Notes; Stone Napa Dispute - Timeline Chronology Binder; Ashbury - Def's MSJ Binder; Ashbury - Unlabeled Binder - Engman Deposition Transcript; Sean Sharma - Unlabeled Binder; MISC FINRA Binded Docs; Sean Sharma - Working Binder Box 2: Polychain v. Greenhouse --> Cases & Authorities in Briefs Binder; Delaware Chancery Court Deocuments Binder; Claimant's Opening Brief Binder; Claimant's Requests for Attorney's Fees and Costs Binder; Polychain Financial Statements - Redwell; Loose Docs Box 3: Polychain v. Greenhouse --> Arbitration Demand & Briefs Binder; Respondent's Opposition to Claimant's Opening Briefs Binder; MISC Docs of Polychain & Rosenblood; Other --> Jeff & Vina Deposition Preparation; Sharma Depo Prep Volumes 1 & 2 Box 4: Carbon --> Chronology by Module Binder; FINRA Arbitration Binder; SEC Enforcement Cases - Redwell Box 5: Orion --> MTD First Amdended Complaint Vol. 1 & 2 Binders; Discovery Hearing Binder Box 6: Soutirage --> 6/22 JAMS Arbitration Hearing Binder; Soutirage's Abritration Binder (x4); Gundlach Claimant's Arbitration Exhibits; Original/Sealed Transcript 6/22/18; MISC Notes & Transcripts; Exhibits Redwell Box 7: Several MISC Manila Folders - All cases
A215: JNH - Stone WPP Binders | B215: R102648291 | C215: Folder - Noah's "Trial Binder?" tabs etc.; WPP Deposition Modules Binder; Master Chronology III. Covid Lease Dispute binder"
A216: PLV Docs | B216: R102153862 | C216: Babyganics product Ingredients binder, Connecticut Gen Lfie Insurance exhibit binder
A217: Beach Nut | B217: R102153865 | C217: Pre/post trial breifs
A218: B & G | B218: R102153870 | C218: Misc Docs/Research, Stock Purchase agreements & plan of merger, andry v. B&G, initial diclosures + CD,2 notebooks, Renee kwah James Arbitration Binder, Babyganics misc docs cases redwells
A219: Energy team | B219: R102153871 | C219: Settlement Statement, key cases, key docs, opposition to motio9n to vacate arrest warrant, settlement material, motion to vacate arrest warrant, misc docs; Pirate 2013 market overview,
A220: Previous entry continued | C220: 1927 Opp Docs, rule ll opp, B&G court decision binder
A221: Paron | B221: R102153879 | C221: NFA chronology, Demurrer Binder, Kass's Mediation Breif, Hedge fund litigation binder, Motion to compel 3 Hearing Binder, misc docs; Babyganics product testing binder, BG- Jones Docs
A222: Previous entry continued | C222: Plaintiffs confidential mediation statement binder
A223: Lyell | B223: R102153880 | C223: Confidential meditaion statement binder, transcripts and depo notes (vol. 182) binder, EX 1-188 Binder, Modules for mdeiation Binder, Bennitt/Berry/Connell/Tuck extraction binder, misc notepads redwells
A224: Lyell | B224: R102153881 | C224: Confidential mediation statement binder, misc manilla folders, binders, redwells, JNH working binder, Bennitt/Berry/Connell/Tuck extraction binder, 2017-02-08 letter request binder, expert materials binder
A225: Lyell | B225: R102153882 | C225: Misc research + reports
A226: Lyell | B226: R102153883 | C226: MBB working binder, joint submission by Puglia and BAE systems Binder, Donald Heberk Communications Redwell, Bennitt/Berry/Connell/Tuck Extraction Binder
A227: no discernable description | B227: R102153884 | C227: Trial Prep Binder, misc research notepads, Eva Misc, lyell, eCurrency, Tyrell Redwells, Folders, Notepads
A228: Lyell | B228: R102153885 | C228: Intersting Emails Binder, Transcripts
A229: Taunton | B229: R102266397 | C229: Nancy Docs Redwell, Misc Documents Redwells
A230: no discernable description | B230: R102153873 | C230: Carlos Ortega Docket Redwell; Newport trial hot docs redwell; Moodcast misc folders and research
A231: Donald Golden | B231: R102266938 | C231: Pleadings folders, Correspondence Folders, Apellate Court Rules Folder
A232: Donald Golden | B232: R102266939 | C232: Deposition Transcripts
A233: Babyganics | B233: R102153876 | C233: Confidential mediation binder, Brand Studies Binder, Product Ingredients Binder, Misc research notes EKS 8/17/17, Misc research papers
A234: EKS 8/17/17 | B234: R102153874 | C234: Misc research, papers, redwells; Rainsy decl. and exhibits binders; Golden CEP production, draft trial exhibits, sealed depos
A235: Golden | B235: R102153869 | C235: Production
A236: Healtchcare facility agreement docs | B236: R102153868
A237: Healtchcare facility agreement docs | B237: R102153867 | C237: Huffman Sara, misc research
A238: Multiple Case Documents | B238: R102153866 | C238: Ashbury misc research, notes; Babyganics brand study binder; Optronic mediation statement binder; Golden Misc folders; Nature's Bakery trademark research report
A239: Multiple Case Documents | B239: R102266940 | C239: Sam Rainsey Hearing binder; Foster Farms water records; Arreola court transcripts; Lyell hearing binder; CANHR misc docs redwell; Bhatt misc docs redwell; CANHR misc documents binder
A240: Golden | B240: R102266941 | C240: Deposition Transcripts
A241: Multiple Case Documents | B241: R102266942 | C241: Rainsy research binder; CANHR misc research redwells; eCurrency working binder; Tiahrt research redwell; Delman brand production redwell; NB conflict docs Redwell
A242: Multiple Case Documents | B242: R102266943 | C242: Orion meidation Binder; Kunesch misc docs, research; Lyell Decl. and Exhibits
A243: Multiple Case Documents | B243: R102266944 | C243: Orion misc documents, redwells, reports; Pirates caselaw research files redwell
A244: Multiple Case Documents | B244: R102266945 | C244: Pirates Mot. To transfer Binder; Opp Binder; GMO docs Binder; Ashbury Heights chronology binder, mediation breifs, motion, appendix, appealdocs redwell
A245: Multiple Case Documents | B245: R102266946 | C245: Ashbury appeal docs redwell, misc docs, motion, appendix, breif; CANHR misc docs, research; Orion notes
...
